xnbtd/__init__.py
xnbtd/admin.py
xnbtd/analytics/__init__.py
xnbtd/analytics/admin.py
xnbtd/analytics/apps.py
xnbtd/analytics/export.py
xnbtd/analytics/migrations/0001_initial.py
xnbtd/analytics/migrations/0002_alter_expense_options.py
xnbtd/analytics/migrations/__init__.py
xnbtd/analytics/models.py
xnbtd/analytics/templatetags/__init__.py
xnbtd/analytics/templatetags/pricing.py
xnbtd/analytics/tests.py
xnbtd/analytics/urls.py
xnbtd/analytics/views.py
xnbtd/apps.py
xnbtd/asgi.py
xnbtd/locale/fr/LC_MESSAGES/django.mo
xnbtd/locale/fr/LC_MESSAGES/django.po
xnbtd/plannings/__init__.py
xnbtd/plannings/admin.py
xnbtd/plannings/apps.py
xnbtd/plannings/forms.py
xnbtd/plannings/locale/fr/LC_MESSAGES/django.mo
xnbtd/plannings/locale/fr/LC_MESSAGES/django.po
xnbtd/plannings/migrations/0001_initial.py
xnbtd/plannings/migrations/0002_rest.py
xnbtd/plannings/migrations/__init__.py
xnbtd/plannings/models.py
xnbtd/publish.py
xnbtd/settings/__init__.py
xnbtd/settings/base.py
xnbtd/settings/local.py
xnbtd/settings/prod.py
xnbtd/settings/test.py
xnbtd/templates/xnbtd/admin/change_form.html
xnbtd/templates/xnbtd/admin/change_list.html
xnbtd/templates/xnbtd/admin/gls_change_list.html
xnbtd/templates/xnbtd/admin/index.html
xnbtd/templatetags/events.py
xnbtd/templatetags/tours.py
xnbtd/tours/__init__.py
xnbtd/tours/admin.py
xnbtd/tours/apps.py
xnbtd/tours/locale/fr/LC_MESSAGES/django.mo
xnbtd/tours/locale/fr/LC_MESSAGES/django.po
xnbtd/tours/migrations/0001_initial.py
xnbtd/tours/migrations/0002_chronopostdelivery_comments_and_more.py
xnbtd/tours/migrations/0003_remove_chronopostdelivery_total_hour_and_more.py
xnbtd/tours/migrations/0004_remove_chronopostdelivery_breaks_and_more.py
xnbtd/tours/migrations/0005_alter_breaktime_options.py
xnbtd/tours/migrations/0006_remove_breaktime_time_breaktime_end_time_and_more.py
xnbtd/tours/migrations/0007_ciblex_relais.py
xnbtd/tours/migrations/0008_alter_breaktime_options_and_more.py
xnbtd/tours/migrations/0009_alter_breaktime_options_and_more.py
xnbtd-2.0.3.dist-info/LICENSE
xnbtd-2.0.3.dist-info/METADATA
xnbtd-2.0.3.dist-info/WHEEL
xnbtd-2.0.3.dist-info/entry_points.txt
xnbtd-2.0.3.dist-info/RECORD
