Metadata-Version: 2.3
Name: xnbtd
Version: 2.0.3
Summary: xNBTD est une application de gestion pour entreprise de livraison. Elle facilite la gestion des tournées et des plannings.
License: GPL-3.0-or-later
Author: André Théo LAURET
Author-email: andrelauret@eclipse-technology.eu
Maintainer: André Théo LAURET
Maintainer-email: andrelauret@eclipse-technology.eu
Requires-Python: >=3.9,<4.0.0
Classifier: License :: OSI Approved :: GNU General Public License v3 or later (GPLv3+)
Classifier: Programming Language :: Python :: 3
Classifier: Programming Language :: Python :: 3.9
Classifier: Programming Language :: Python :: 3.10
Classifier: Programming Language :: Python :: 3.11
Classifier: Programming Language :: Python :: 3.12
Classifier: Programming Language :: Python :: 3.13
Requires-Dist: pip (>=23.1.2,<24.0.0)
Project-URL: Bug Tracker, https://github.com/eldertek/xnbtd/issues
Project-URL: Homepage, https://github.com/eldertek/xnbtd
